wanikani_api/__init__.py
wanikani_api/client.py
wanikani_api/constants.py
wanikani_api/exceptions.py
wanikani_api/models.py
wanikani_api/subjectcache.py
wanikani_api/url_builder.py
wanikani_api-0.6.1.dist-info/AUTHORS.rst
wanikani_api-0.6.1.dist-info/LICENSE
wanikani_api-0.6.1.dist-info/METADATA
wanikani_api-0.6.1.dist-info/WHEEL
wanikani_api-0.6.1.dist-info/top_level.txt
wanikani_api-0.6.1.dist-info/RECORD
