Metadata-Version: 2.1
Name: wanikani-api
Version: 0.6.1
Summary: An API wrapper for Wanikani (V2)
Home-page: https://github.com/Kaniwani/wanikani_api
Author: Gary Grant Graham
Author-email: gary@kaniwani.com
License: BSD license
Keywords: wanikani_api
Platform: UNKNOWN
Classifier: Development Status :: 2 - Pre-Alpha
Classifier: Intended Audience :: Developers
Classifier: License :: OSI Approved :: BSD License
Classifier: Natural Language :: English
Classifier: Programming Language :: Python :: 3.6
Classifier: Programming Language :: Python :: 3.7
License-File: LICENSE
License-File: AUTHORS.rst
Requires-Dist: requests
Requires-Dist: python-dateutil
